fst/__init__.py
fst/__main__.py
fst/asttypes.py
fst/astutil.py
fst/code.py
fst/common.py
fst/fst.py
fst/fst_accessors.py
fst/fst_core.py
fst/fst_get_one.py
fst/fst_get_slice.py
fst/fst_locs.py
fst/fst_misc.py
fst/fst_options.py
fst/fst_put_one.py
fst/fst_put_slice.py
fst/fst_raw.py
fst/fst_traverse.py
fst/fst_type_predicates.py
fst/fuzz.py
fst/parsex.py
fst/py.typed
fst/reconcile.py
fst/slice_exprlike.py
fst/slice_stmtlike.py
fst/traverse_next.py
fst/traverse_prev.py
fst/view.py
fst/docs/__init__.py
fst/docs/d01_parse.py
fst/docs/d02_locations.py
fst/docs/d03_structure.py
fst/docs/d04_get.py
fst/docs/d05_put.py
fst/docs/d06_slices.py
fst/docs/d07_views.py
fst/docs/d08_coerce.py
fst/docs/d09_parentheses.py
fst/docs/d10_options.py
fst/docs/d11_raw.py
fst/docs/d12_reconcile.py
fst/docs/d13_examples.py
pfst-0.2.6.dist-info/licenses/LICENSE
pfst-0.2.6.dist-info/METADATA
pfst-0.2.6.dist-info/WHEEL
pfst-0.2.6.dist-info/top_level.txt
pfst-0.2.6.dist-info/RECORD
