Metadata-Version: 2.4
Name: pfst
Version: 0.2.6
Summary: Format-preserving high level AST editing for Python 3.10+.
Author-email: Tomasz Pytel <tompytel@gmail.com>
License-Expression: MIT
Project-URL: Repository, https://github.com/tom-pytel/pfst
Project-URL: Documentation, https://tom-pytel.github.io/pfst/
Project-URL: PyPI, https://pypi.org/project/pfst/
Keywords: ast,python,python-ast,code-transform,refactoring,syntax-tree,code-analysis,format-preserving,source-editing,code-rewriting
Classifier: Development Status :: 3 - Alpha
Classifier: Intended Audience :: Developers
Classifier: Programming Language :: Python :: 3
Classifier: Programming Language :: Python :: 3.10
Classifier: Programming Language :: Python :: 3.11
Classifier: Programming Language :: Python :: 3.12
Classifier: Programming Language :: Python :: 3.13
Classifier: Programming Language :: Python :: 3.14
Classifier: Topic :: Software Development
Classifier: Topic :: Software Development :: Libraries
Requires-Python: >=3.10
License-File: LICENSE
Provides-Extra: dev
Requires-Dist: build; extra == "dev"
Requires-Dist: setuptools; extra == "dev"
Requires-Dist: wheel; extra == "dev"
Requires-Dist: twine; extra == "dev"
Requires-Dist: pdoc==15.0.1; extra == "dev"
Requires-Dist: ruff==0.12.7; extra == "dev"
Requires-Dist: pytest==9.0.1; extra == "dev"
Requires-Dist: pytest-cov==7.0.0; extra == "dev"
Dynamic: license-file
